lib310/__init__.py
lib310/_settings.py
lib310/data/__init__.py
lib310/data/_base.py
lib310/data/_utils.py
lib310/database/__init__.py
lib310/database/_connection.py
lib310/database/_constants.py
lib310/database/_functions.py
lib310/database/_visualize.py
lib310/database/cache_bgquery.py
lib310/database/charts/bubble_chart.py
lib310/database/client.py
lib310/database/exceptions.py
lib310/database/gcs_dataset.py
lib310/database/mldl.py
lib310/database/models/InteractionModel.py
lib310/database/models/SeqLangModel.py
lib310/lazy_loader.py
lib310/machinelearning/__init__.py
lib310/machinelearning/_base.py
lib310/machinelearning/_goa.py
lib310/machinelearning/_io.py
lib310/machinelearning/_lm.py
lib310/machinelearning/_mlm.py
lib310/tools/TMalign.cpp
lib310/tools/TMscore.cpp
lib310/tools/__init__.py
lib310/tools/_clustering.py
lib310/tools/_pdb.py
lib310/tools/_tmalign.py
lib310/visualization/__init__.py
lib310/visualization/_repr.py
lib310-0.2.66.dist-info/WHEEL
lib310-0.2.66.dist-info/METADATA
lib310-0.2.66.dist-info/RECORD
